MANIFEST.in
README.rst
setup.py
djangocms_complete_slider/__init__.py
djangocms_complete_slider/cms_plugins.py
djangocms_complete_slider/forms.py
djangocms_complete_slider/models.py
djangocms_complete_slider/settings.py
djangocms_complete_slider/tests.py
djangocms_complete_slider.egg-info/PKG-INFO
djangocms_complete_slider.egg-info/SOURCES.txt
djangocms_complete_slider.egg-info/dependency_links.txt
djangocms_complete_slider.egg-info/not-zip-safe
djangocms_complete_slider.egg-info/requires.txt
djangocms_complete_slider.egg-info/top_level.txt
djangocms_complete_slider/migrations/0001_initial.py
djangocms_complete_slider/migrations/0002_auto_20180409_1142.py
djangocms_complete_slider/migrations/__init__.py
djangocms_complete_slider/static/.DS_Store
djangocms_complete_slider/static/djangocms_complete_slider/.DS_Store
djangocms_complete_slider/static/djangocms_complete_slider/css/vegas.min.css
djangocms_complete_slider/static/djangocms_complete_slider/js/vegas.js
djangocms_complete_slider/templates/djangocms_complete_slider/slide.html
djangocms_complete_slider/templates/djangocms_complete_slider/slider.html